[{"name":"Radio Ciudad Music","days":["1","2","3","4","5"],"start":"00:00","ends":"07:00","hour":"00","minutes":"00","locutor":[{"avatar":"autoDj.gif","firsName":"Auto","lastName":"DJ","profileFacebook":"radiociudad.radiociudad","fullName":"Auto DJ","id":"89190735431985481000"}],"id":"3354762413810633500"},{"name":"Radio Ciudad Music","days":["6"],"start":"00:00","ends":"09:00","hour":"00","minutes":"00","locutor":[{"avatar":"autoDj.gif","firsName":"Auto","lastName":"DJ","profileFacebook":"radiociudad.radiociudad","fullName":"Auto DJ","id":"89190735431985481000"}],"id":"863337638556709200"},{"name":"Radio Ciudad Music","days":["0"],"start":"00:00","ends":"09:00","hour":"00","minutes":"00","locutor":[{"avatar":"autoDj.gif","firsName":"Auto","lastName":"DJ","profileFacebook":"radiociudad.radiociudad","fullName":"Auto DJ","id":"89190735431985481000"}],"id":"314563428834666900"},{"name":"Sentimiento de amor Chamamecero","days":["1","2","3","4","5"],"start":"07:00","ends":"09:00","hour":"07","minutes":"00","locutor":[{"avatar":"Juan.jpg","firsName":"Juan Ramon","lastName":"Villalva","profileFacebook":"/juanramon.villalva.31","fullName":"Juan Ramon Villalva","id":"74465262634076931000"}],"id":"943471589228307207"},{"name":"Un Abrazo Radical","days":["6"],"start":"09:00","ends":"13:00","hour":"09","minutes":"00","locutor":[{"avatar":"Daniel2.jpg","firsName":"Daniel","lastName":"Godoy","profileFacebook":"elloku","fullName":"Daniel Godoy","id":"41066811719870011000"}],"id":"87294469693951509"},{"name":"A Toda Potencia","days":["1","2","3","4","5"],"start":"09:00","ends":"13:00","hour":"09","minutes":"00","locutor":[{"avatar":"Daniel2.jpg","firsName":"Daniel","lastName":"Godoy","profileFacebook":"elloku","fullName":"Daniel Godoy","id":"41066811719870011000"}],"id":"930237715967404309"},{"name":"Variaciones Musicales","days":["0"],"start":"09:00","ends":"12:00","hour":"09","minutes":"00","locutor":[{"avatar":"Juan.jpg","firsName":"Juan Ramon","lastName":"Villalva","profileFacebook":"/juanramon.villalva.31","fullName":"Juan Ramon Villalva","id":"74465262634076931000"},{"avatar":"Malvina.jpg","firsName":"Malvina","lastName":"Correa","profileFacebook":"malvina.correa.7","fullName":"Malvina Correa","id":"99079556953094281000"}],"id":"803599899911492509"},{"name":"Radio Ciudad Music","days":["0"],"start":"12:00","ends":"24:00","hour":"12","minutes":"00","locutor":[{"avatar":"autoDj.gif","firsName":"Auto","lastName":"DJ","profileFacebook":"radiociudad.radiociudad","fullName":"Auto DJ","id":"89190735431985481000"}],"id":"593725710648970112"},{"name":"Vidente Francisco","days":["1","2","3","4","5"],"start":"13:00","ends":"13:30","hour":"13","minutes":"00","locutor":[{"avatar":"Vidente.jpg","firsName":"Vidente","lastName":"Francisco","profileFacebook":"#","fullName":"Vidente Francisco","id":"90678883780248691000"}],"id":"97105746124342213"},{"name":"Radio Ciudad Music","days":["6"],"start":"13:00","ends":"17:00","hour":"13","minutes":"00","locutor":[{"avatar":"autoDj.gif","firsName":"Auto","lastName":"DJ","profileFacebook":"radiociudad.radiociudad","fullName":"Auto DJ","id":"89190735431985481000"}],"id":"456571479842778613"},{"name":"Espacio Publicitario","days":["1","2","3","4","5"],"start":"13:30","ends":"14:00","hour":"13","minutes":"30","locutor":[{"avatar":"Publi2.jpg","firsName":"🕑 14Hs ->","lastName":"Entre Amigos y Chamamé","profileFacebook":"#","fullName":"🕑 14Hs -> Entre Amigos y Chamamé","id":"276719119983038351000"}],"id":"737505807963726213"},{"name":"Entre Amigos y Chamamé","days":["1","2","3","4","5"],"start":"14:00","ends":"16:00","hour":"14","minutes":"00","locutor":[{"avatar":"Silvana.jpg","firsName":"Silvana","lastName":"Silva","profileFacebook":"tuwachitiernasmys","fullName":"Silvana Silva","id":"36568081738566951000"},{"avatar":"Mino.jpg","firsName":"Pedro","lastName":"Miño","profileFacebook":"pedro.mino.1232","fullName":"Pedro Miño","id":"51980667899694311000"}],"id":"6575105836090214"},{"name":"Arriba la Tarde","days":["1","2","3","4","5"],"start":"16:00","ends":"18:00","hour":"16","minutes":"00","locutor":[{"avatar":"Merele.jpg","firsName":"Nestor Fabian","lastName":"Merele","profileFacebook":"nestorfabian.merele","fullName":"Nestor Fabian Merele","id":"4467745377225821000"}],"id":"1933424323961564316"},{"name":"Variaciones Musicales","days":["6"],"start":"17:00","ends":"20:00","hour":"17","minutes":"00","locutor":[{"avatar":"Juan.jpg","firsName":"Juan Ramon","lastName":"Villalva","profileFacebook":"/juanramon.villalva.31","fullName":"Juan Ramon Villalva","id":"74465262634076931000"},{"avatar":"Malvina.jpg","firsName":"Malvina","lastName":"Correa","profileFacebook":"malvina.correa.7","fullName":"Malvina Correa","id":"99079556953094281000"}],"id":"1926528528853939717"},{"name":"Permiso Señores soy Chamamé","days":["1","2","3","4","5"],"start":"18:00","ends":"20:30","hour":"18","minutes":"00","locutor":[{"avatar":"Laura.jpg","firsName":"Laura","lastName":"Medina","profileFacebook":"100007205203112","fullName":"Laura Medina","id":"85834302169687451000"}],"id":"3012772871804616618"},{"name":"Radio Ciudad Music","days":["6"],"start":"20:00","ends":"24:00","hour":"20","minutes":"00","locutor":[{"avatar":"autoDj.gif","firsName":"Auto","lastName":"DJ","profileFacebook":"radiociudad.radiociudad","fullName":"Auto DJ","id":"89190735431985481000"}],"id":"729744116171486120"},{"name":"Defendiendo Trediciones","days":["1","2","3","4","5"],"start":"20:30","ends":"21:30","hour":"20","minutes":"30","locutor":[{"avatar":"David.jpg","firsName":"David","lastName":"Gomez","profileFacebook":"100009783664325","fullName":"David Gomez","id":"32920787622180861000"}],"id":"865031378907079220"},{"name":"Radio Ciudad Music","days":["1","2","3","4","5"],"start":"21:30","ends":"24:00","hour":"21","minutes":"30","locutor":[{"avatar":"autoDj.gif","firsName":"Auto","lastName":"DJ","profileFacebook":"radiociudad.radiociudad","fullName":"Auto DJ","id":"89190735431985481000"}],"id":"394510289043658121"}]